odoo9_addon_website_event_share-9.0.1.0.0-py2.7-nspkg.pth
odoo9_addon_website_event_share-9.0.1.0.0.dist-info/top_level.txt
odoo9_addon_website_event_share-9.0.1.0.0.dist-info/WHEEL
odoo9_addon_website_event_share-9.0.1.0.0.dist-info/RECORD
odoo9_addon_website_event_share-9.0.1.0.0.dist-info/metadata.json
odoo9_addon_website_event_share-9.0.1.0.0.dist-info/DESCRIPTION.rst
odoo9_addon_website_event_share-9.0.1.0.0.dist-info/METADATA
odoo9_addon_website_event_share-9.0.1.0.0.dist-info/namespace_packages.txt
odoo_addons/website_event_share/__openerp__.py
odoo_addons/website_event_share/__init__.py
odoo_addons/website_event_share/README.rst
odoo_addons/website_event_share/views/website_event.xml
odoo_addons/website_event_share/static/description/icon.png
